<?xml version="1.0" encoding="UTF-8"?>
<uml:Model xmi:version="20131001" xmlns:xmi="http://www.omg.org/spec/XMI/20131001" xmlns:uml="http://www.eclipse.org/uml2/5.0.0/UML" xmi:id="_6xS4EFcFEe2Lh7ARxPB2PQ" name="RM_ClassDiagrams">
  <packageImport xmi:type="uml:PackageImport" xmi:id="_6xr5oFcFEe2Lh7ARxPB2PQ">
    <importedPackage xmi:type="uml:Model" href="pathmap://UML_LIBRARIES/UMLPrimitiveTypes.library.uml#_0"/>
  </packageImport>
  <packagedElement xmi:type="uml:Model" xmi:id="_MSpO8FcGEe2Lh7ARxPB2PQ" name="MemberModel">
    <packagedElement xmi:type="uml:Class" xmi:id="_Q8K-0FcGEe2Lh7ARxPB2PQ" name="Member" visibility="package">
      <ownedOperation xmi:type="uml:Operation" xmi:id="_AGBdMOW1Ee2GOddCZBzsXQ" name="getAge">
        <ownedParameter xmi:type="uml:Parameter" xmi:id="_GdA0cOW1Ee2GOddCZBzsXQ" direction="return">
          <type xmi:type="uml:PrimitiveType" href="pathmap://UML_LIBRARIES/UMLPrimitiveTypes.library.uml#Integer"/>
        </ownedParameter>
      </ownedOperation>
      <ownedOperation xmi:type="uml:Operation" xmi:id="_AXoKkOW1Ee2GOddCZBzsXQ" name="gateName">
        <ownedParameter xmi:type="uml:Parameter" xmi:id="_J0cqUOW1Ee2GOddCZBzsXQ" direction="return">
          <type xmi:type="uml:PrimitiveType" href="pathmap://UML_LIBRARIES/UMLPrimitiveTypes.library.uml#String"/>
        </ownedParameter>
      </ownedOperation>
      <ownedOperation xmi:type="uml:Operation" xmi:id="_R8r8wOW1Ee2GOddCZBzsXQ" name="isActive">
        <ownedParameter xmi:type="uml:Parameter" xmi:id="_R8r8weW1Ee2GOddCZBzsXQ" direction="return">
          <type xmi:type="uml:PrimitiveType" href="pathmap://UML_LIBRARIES/UMLPrimitiveTypes.library.uml#Boolean"/>
        </ownedParameter>
      </ownedOperation>
    </packagedElement>
    <packagedElement xmi:type="uml:Class" xmi:id="_YzXtsOUmEe2AC7Km8iR5Nw" name="Class2"/>
  </packagedElement>
</uml:Model>
